LICENSE
MANIFEST.in
README.rst
setup.py
home/__init__.py
home/models.py
home/migrations/0001_initial.py
home/migrations/0002_create_homepage.py
home/migrations/__init__.py
testapp/settings/__init__.py
testapp/settings/base.py
testapp/settings/dev.py
testapp/settings/production.py
wagtail_knowledgebase.egg-info/PKG-INFO
wagtail_knowledgebase.egg-info/SOURCES.txt
wagtail_knowledgebase.egg-info/dependency_links.txt
wagtail_knowledgebase.egg-info/not-zip-safe
wagtail_knowledgebase.egg-info/requires.txt
wagtail_knowledgebase.egg-info/top_level.txt
wtknowledgebase/__init__.py
wtknowledgebase/apps.py
wtknowledgebase/blocks.py
wtknowledgebase/models.py
wtknowledgebase/tests.py
wtknowledgebase/migrations/0001_initial.py
wtknowledgebase/migrations/0002_alter_body.py
wtknowledgebase/migrations/__init__.py
wtknowledgebase/templates/wtknowledgebase/base.html
wtknowledgebase/templates/wtknowledgebase/card_block.html
wtknowledgebase/templates/wtknowledgebase/grid_cell_block.html
wtknowledgebase/templates/wtknowledgebase/grid_row_block.html
wtknowledgebase/templates/wtknowledgebase/jumbotron_block.html
wtknowledgebase/templates/wtknowledgebase/kb_article_page.html
wtknowledgebase/templates/wtknowledgebase/kb_category_page.html
wtknowledgebase/templates/wtknowledgebase/kb_index_page.html