Metadata-Version: 2.1
Name: wagtail-knowledgebase
Version: 1.0
Summary: Knowledgebase pages with bootstrap compatible StreamFields configured
Home-page: https://github.com/skruger/wagtail-knowledgebase
Author: Shaun Kruger
Author-email: shaun.kruger@gmail.com
License: The MIT License: http://www.opensource.org/licenses/mit-license.php
Platform: all
Classifier: Environment :: Web Environment
Classifier: Intended Audience :: Developers
Classifier: License :: OSI Approved :: MIT License
Classifier: Operating System :: OS Independent
Classifier: Programming Language :: Python
Classifier: Framework :: Django
License-File: LICENSE
